lumen_resources/__init__.py
lumen_resources/cli.py
lumen_resources/downloader.py
lumen_resources/exceptions.py
lumen_resources/lumen_config.py
lumen_resources/lumen_config_validator.py
lumen_resources/model_info.py
lumen_resources/model_info_validator.py
lumen_resources/platform.py
lumen_resources/result_schemas/README.md
lumen_resources/result_schemas/__init__.py
lumen_resources/result_schemas/embedding_v1.py
lumen_resources/result_schemas/face_v1.py
lumen_resources/result_schemas/labels_v1.py
lumen_resources/result_schemas/ocr_v1.py
lumen_resources/result_schemas/text_generation_v1.py
lumen_resources/schemas/config-schema.yaml
lumen_resources/schemas/model_info-schema.json
lumen_resources/schemas/result_schemas/embedding_v1.json
lumen_resources/schemas/result_schemas/face_v1.json
lumen_resources/schemas/result_schemas/labels_v1.json
lumen_resources/schemas/result_schemas/ocr_v1.json
lumen_resources/schemas/result_schemas/text_generation_v1.json
lumen_resources-0.4.1.dist-info/METADATA
lumen_resources-0.4.1.dist-info/WHEEL
lumen_resources-0.4.1.dist-info/entry_points.txt
lumen_resources-0.4.1.dist-info/top_level.txt
lumen_resources-0.4.1.dist-info/RECORD
