Metadata-Version: 2.4
Name: lumen-resources
Version: 0.4.1
Summary: Unified model resource management for Lumen ML services
Author-email: EdwinZhanCN <support@lumilio.org>
License: MIT
Project-URL: Homepage, https://github.com/EdwinZhanCN/Lumen
Project-URL: Issues, https://github.com/EdwinZhanCN/Lumen/issues
Requires-Python: >=3.10
Requires-Dist: huggingface_hub>=0.20.0
Requires-Dist: modelscope>=1.11.0
Requires-Dist: pydantic>=2.0.0
Requires-Dist: jsonschema>=4.0.0
Provides-Extra: dev
Requires-Dist: pytest>=7.0.0; extra == "dev"
Requires-Dist: pytest-cov>=4.0.0; extra == "dev"
Requires-Dist: black>=23.0.0; extra == "dev"
Requires-Dist: ruff>=0.1.0; extra == "dev"
Requires-Dist: datamodel-code-generator[http]>=0.25.0; extra == "dev"
Requires-Dist: pre-commit>=3.0.0; extra == "dev"
Provides-Extra: config
Requires-Dist: pyyaml>=6.0.0; extra == "config"
